[
  {
    "id" : 734,
    "genre" : "dfdf",
    "author" : "dfdfd",
    "source" : "dfdfd",
    "label" : "dfdfd",
    "date" : "2020-09-08",
    "on_spotify" : true
  },
  {
    "id" : 709,
    "genre" : "rerer",
    "author" : "ffsf",
    "source" : "htht",
    "label" : "hvcbcb",
    "date" : "2020-07-06",
    "on_spotify" : false
  },
  {
    "id" : 640,
    "genre" : "eewew",
    "author" : "wewew",
    "source" : "ererer",
    "label" : "rttytyty",
    "date" : "2020-03-02",
    "on_spotify" : true
  },
  {
    "id" : 261,
    "genre" : {
      "id" : 398,
      "name" : "ssd"
    },
    "author" : "sdsd",
    "source" : "sds",
    "label" : "ds",
    "date" : "2020-02-02",
    "on_spotify" : true
  },
  {
    "id" : 660,
    "genre" : "sdsds",
    "author" : "sdsds",
    "source" : "rrgrgr",
    "label" : "yhyyjyj",
    "date" : "2020-08-02",
    "on_spotify" : false
  },
  {
    "id" : 123,
    "genre" : "sdsds",
    "author" : "wewe",
    "source" : "wewe",
    "label" : "yhyyjyj",
    "date" : "2020-01-04",
    "on_spotify" : false
  },
  {
    "id" : 984,
    "genre" : "sdsd",
    "author" : "sdsds",
    "source" : "sdsdsd",
    "label" : "sdsdsd",
    "date" : "2020-01-01",
    "on_spotify" : false
  }
]